nayombi/__init__.py
nayombi/core.py
nayombi/database.py
nayombi/helper.py
nayombi/models.py
tests/__init__.py
tests/test_access_policy.py
tests/test_database.py
nayombi-1.3.0.dist-info/LICENSE
nayombi-1.3.0.dist-info/METADATA
nayombi-1.3.0.dist-info/WHEEL
nayombi-1.3.0.dist-info/top_level.txt
nayombi-1.3.0.dist-info/RECORD
